[{"path":"stored/cartelladiciao","name":"cartelladiciao","children":[{"path":"stored/cartelladiciao/dvds","name":"dvds","size":0,"type":"file","extension":""},{"path":"stored/cartelladiciao/ola","name":"ola","children":[{"path":"stored/cartelladiciao/ola/asaka","name":"asaka","size":0,"type":"file","extension":""}],"size":0,"type":"directory"}],"size":0,"type":"directory"},{"path":"stored/cartellasium","name":"cartellasium","children":[{"path":"stored/cartellasium/cartellasub","name":"cartellasub","children":[{"path":"stored/cartellasium/cartellasub/ciaone","name":"ciaone","size":0,"type":"file","extension":""}],"size":0,"type":"directory"},{"path":"stored/cartellasium/gianni","name":"gianni","size":0,"type":"file","extension":""}],"size":0,"type":"directory"},{"path":"stored/ciao","name":"ciao","size":13,"type":"file","extension":""},{"path":"stored/ciao2","name":"ciao2","size":0,"type":"file","extension":""},{"path":"stored/ciao3","name":"ciao3","size":0,"type":"file","extension":""}]